foliant/preprocessors/runcommands.py
foliantcontrib.runcommands-1.0.1.dist-info/LICENSE
foliantcontrib.runcommands-1.0.1.dist-info/METADATA
foliantcontrib.runcommands-1.0.1.dist-info/WHEEL
foliantcontrib.runcommands-1.0.1.dist-info/top_level.txt
foliantcontrib.runcommands-1.0.1.dist-info/RECORD
